neo4j_haystack/__about__.py
neo4j_haystack/__init__.py
neo4j_haystack/errors.py
neo4j_haystack/client/__init__.py
neo4j_haystack/client/neo4j_client.py
neo4j_haystack/components/__init__.py
neo4j_haystack/components/neo4j_query_reader.py
neo4j_haystack/components/neo4j_query_writer.py
neo4j_haystack/components/neo4j_retriever.py
neo4j_haystack/document_stores/__init__.py
neo4j_haystack/document_stores/neo4j_store.py
neo4j_haystack/document_stores/utils.py
neo4j_haystack/metadata_filter/__init__.py
neo4j_haystack/metadata_filter/neo4j_query_converter.py
neo4j_haystack/metadata_filter/parser.py
neo4j_haystack/serialization/__init__.py
neo4j_haystack/serialization/query_parameters_marshaller.py
neo4j_haystack/serialization/types.py
neo4j_haystack-2.2.1.dist-info/METADATA
neo4j_haystack-2.2.1.dist-info/WHEEL
neo4j_haystack-2.2.1.dist-info/licenses/LICENSE.txt
neo4j_haystack-2.2.1.dist-info/RECORD
