Metadata-Version: 2.4
Name: neo4j-haystack
Version: 2.2.1
Summary: Integration of Neo4j graph database with Haystack
Project-URL: Documentation, https://prosto.github.io/neo4j-haystack
Project-URL: Issues, https://github.com/prosto/neo4j-haystack/issues
Project-URL: Source, https://github.com/prosto/neo4j-haystack
Author-email: Sergey Bondarenco <sergey.bondarenco@outlook.com>
License-Expression: MIT
License-File: LICENSE.txt
Keywords: DocumentStore,Haystack,neo4j,semantic-search
Classifier: Development Status :: 4 - Beta
Classifier: Operating System :: OS Independent
Classifier: Programming Language :: Python
Classifier: Programming Language :: Python :: 3.9
Classifier: Programming Language :: Python :: 3.10
Classifier: Programming Language :: Python :: 3.11
Classifier: Programming Language :: Python :: 3.12
Classifier: Programming Language :: Python :: Implementation :: CPython
Classifier: Programming Language :: Python :: Implementation :: PyPy
Requires-Python: >=3.9
Requires-Dist: haystack-ai>=2.6.0
Requires-Dist: neo4j>=5.8.1
Provides-Extra: all
Requires-Dist: black>=24.8.0; extra == 'all'
Requires-Dist: coverage[toml]>=7.6.1; extra == 'all'
Requires-Dist: datasets; extra == 'all'
Requires-Dist: docker; extra == 'all'
Requires-Dist: git-changelog>=2.5.2; extra == 'all'
Requires-Dist: mkdocs-coverage>=1.1.0; extra == 'all'
Requires-Dist: mkdocs-material>=9.5.34; extra == 'all'
Requires-Dist: mkdocs-section-index>=0.3.9; extra == 'all'
Requires-Dist: mkdocs>=1.6.1; extra == 'all'
Requires-Dist: mkdocstrings[python]; extra == 'all'
Requires-Dist: mypy>=1.11.2; extra == 'all'
Requires-Dist: numpy<2; extra == 'all'
Requires-Dist: pytest; extra == 'all'
Requires-Dist: ruff>=0.6.5; extra == 'all'
Requires-Dist: sentence-transformers>=3.1.0; extra == 'all'
Provides-Extra: docker
Requires-Dist: docker; extra == 'docker'
Provides-Extra: docs
Requires-Dist: black>=24.8.0; extra == 'docs'
Requires-Dist: mkdocs-coverage>=1.1.0; extra == 'docs'
Requires-Dist: mkdocs-material>=9.5.34; extra == 'docs'
Requires-Dist: mkdocs-section-index>=0.3.9; extra == 'docs'
Requires-Dist: mkdocs>=1.6.1; extra == 'docs'
Requires-Dist: mkdocstrings[python]; extra == 'docs'
Provides-Extra: examples
Requires-Dist: datasets; extra == 'examples'
Provides-Extra: maintain
Requires-Dist: git-changelog>=2.5.2; extra == 'maintain'
Provides-Extra: quality
Requires-Dist: black>=24.8.0; extra == 'quality'
Requires-Dist: ruff>=0.6.5; extra == 'quality'
Provides-Extra: tests
Requires-Dist: coverage[toml]>=7.6.1; extra == 'tests'
Requires-Dist: docker; extra == 'tests'
Requires-Dist: numpy<2; extra == 'tests'
Requires-Dist: pytest; extra == 'tests'
Requires-Dist: sentence-transformers>=3.1.0; extra == 'tests'
Provides-Extra: typing
Requires-Dist: mypy>=1.11.2; extra == 'typing'
